nb_code_formatter/__init__.py
nb_code_formatter-0.1.1.dist-info/entry_points.txt
nb_code_formatter-0.1.1.dist-info/LICENSE
nb_code_formatter-0.1.1.dist-info/WHEEL
nb_code_formatter-0.1.1.dist-info/METADATA
nb_code_formatter-0.1.1.dist-info/RECORD
